clipcraft/__init__.py
clipcraft/create_embeddings.py
clipcraft/knn_search.py
clipcraft-1.4.6.dist-info/METADATA
clipcraft-1.4.6.dist-info/WHEEL
clipcraft-1.4.6.dist-info/top_level.txt
clipcraft-1.4.6.dist-info/RECORD
