Metadata-Version: 2.1
Name: clipcraft
Version: 1.4.6
Summary: A package for CLIP-based image and text processing.
Home-page: https://github.com/mmckenzieORCEN/CLIPCraft
Author: Morgan McKenzie
Author-email: morgancmckenziecs@gmail.com
Requires-Dist: transformers
Requires-Dist: Pillow
Requires-Dist: numpy
Requires-Dist: requests
